{
  "project_info": {
    "project_number": "667661109814",
    "project_id": "imagesharingapp-72f51",
    "storage_bucket": "imagesharingapp-72f51.appspot.com"
  },
  "client": [
    {
      "client_info": {
        "mobilesdk_app_id": "1:667661109814:android:bdbe49fceda8e52a31a697",
        "android_client_info": {
          "package_name": "com.berkaysenkoylu.imagesharingapp"
        }
      },
      "oauth_client": [
        {
          "client_id": "667661109814-d1e8l7mvfvr54qede9p05giep0so1na8.apps.googleusercontent.com",
          "client_type": 3
        }
      ],
      "api_key": [
        {
          "current_key": "AIzaSyAjRWtmz3n7jga2PI-qZxYC_7Y_KbJi50M"
        }
      ],
      "services": {
        "appinvite_service": {
          "other_platform_oauth_client": [
            {
              "client_id": "667661109814-d1e8l7mvfvr54qede9p05giep0so1na8.apps.googleusercontent.com",
              "client_type": 3
            }
          ]
        }
      }
    }
  ],
  "configuration_version": "1"
}